dinoop_cdxgenscan/__init__.py
dinoop_cdxgenscan/main.py
dinoop_syftscan/__init__.py
dinoop_syftscan/main.py
dinoop_source_repo_scans-0.1.0.dist-info/METADATA
dinoop_source_repo_scans-0.1.0.dist-info/WHEEL
dinoop_source_repo_scans-0.1.0.dist-info/top_level.txt
dinoop_source_repo_scans-0.1.0.dist-info/RECORD
