Metadata-Version: 2.2
Name: dinoop_source_repo_scans
Version: 0.1.0
Summary: package for source repo
Author-email: dinoop <dinoop@example.com>
